{
  "generator-jhipster": {
    "promptValues": {
      "packageName": "com.mycompany.myapp",
      "nativeLanguage": "en"
    },
    "jhipsterVersion": "6.0.0",
    "applicationType": "monolith",
    "baseName": "prueba",
    "packageName": "com.mycompany.myapp",
    "packageFolder": "com/mycompany/myapp",
    "serverPort": "8080",
    "authenticationType": "jwt",
    "cacheProvider": "ehcache",
    "enableHibernateCache": true,
    "websocket": false,
    "databaseType": "sql",
    "devDatabaseType": "mysql",
    "prodDatabaseType": "mysql",
    "searchEngine": "elasticsearch",
    "messageBroker": false,
    "serviceDiscoveryType": false,
    "buildTool": "maven",
    "enableSwaggerCodegen": false,
    "jwtSecretKey": "OWU0MDg3MTdiZmRiOWUyYjM5NWUxMDFlNWNmNjdhNDc3MWJmOTAxZjNlMzk4NjYyZDAzMTZiNDcxZWJhNzg0ZjM4OWE0OWM3NDI0ZWFkYjM5YmY1YmRlYmY2MjdhN2QyZDY2MTVjODg4ODJjNWQ0Mzc1ZWM4YmYxNWI3N2U4NGE=",
    "clientFramework": "angularX",
    "clientTheme": "none",
    "clientThemeVariant": "",
    "useSass": true,
    "clientPackageManager": "npm",
    "testFrameworks": [],
    "jhiPrefix": "jhi",
    "entitySuffix": "",
    "dtoSuffix": "DTO",
    "otherModules": [],
    "enableTranslation": true,
    "nativeLanguage": "en",
    "languages": ["en", "es"]
  }
}
